oneocr.py
oneocr-1.0.10.dist-info/METADATA
oneocr-1.0.10.dist-info/WHEEL
oneocr-1.0.10.dist-info/entry_points.txt
oneocr-1.0.10.dist-info/top_level.txt
oneocr-1.0.10.dist-info/RECORD
