Metadata-Version: 2.4
Name: oneocr
Version: 1.0.10
Summary: Snipping Tool OCR for Windows
Author: Cecilia-pj, b1tg
Author-email: Aurora Wright <fallingluma@gmail.com>
License-Expression: MIT
Project-URL: Homepage, https://github.com/AuroraWright/oneocr
Classifier: Programming Language :: Python :: 3
Classifier: Operating System :: Microsoft :: Windows :: Windows 10
Requires-Python: >=3
Requires-Dist: Pillow
Provides-Extra: api
Requires-Dist: fastapi; extra == "api"
Requires-Dist: uvicorn; extra == "api"
Provides-Extra: cv2
Requires-Dist: opencv-python; extra == "cv2"
Provides-Extra: all
Requires-Dist: fastapi; extra == "all"
Requires-Dist: uvicorn; extra == "all"
Requires-Dist: opencv-python; extra == "all"
